README.md
setup.py
revent/__init__.py
revent/__main__.py
revent.egg-info/PKG-INFO
revent.egg-info/SOURCES.txt
revent.egg-info/dependency_links.txt
revent.egg-info/requires.txt
revent.egg-info/top_level.txt