Metadata-Version: 2.1
Name: revent
Version: 1.4
Summary: Event util base on Redis
Home-page: https://github.com/lwzm/revent
Author: lwzm
Author-email: lwzm@qq.com
License: UNKNOWN
Keywords: redis,event,util
Platform: UNKNOWN
Classifier: Environment :: Console
Classifier: Programming Language :: Python :: 3
Classifier: Programming Language :: Python :: 3.5
Classifier: Programming Language :: Python :: 3.6
Classifier: Programming Language :: Python :: 3.7
Classifier: Programming Language :: Python :: Implementation :: CPython
Classifier: Programming Language :: Python :: Implementation :: PyPy
Classifier: Topic :: Software Development :: Libraries :: Python Modules
Classifier: License :: OSI Approved :: MIT License
